plumberhub/Client.py
plumberhub/__init__.py
plumberhub/plumberhub_pb2.py
plumberhub_client-0.3.0.dist-info/LICENSE
plumberhub_client-0.3.0.dist-info/METADATA
plumberhub_client-0.3.0.dist-info/WHEEL
plumberhub_client-0.3.0.dist-info/top_level.txt
plumberhub_client-0.3.0.dist-info/RECORD
