Metadata-Version: 2.1
Name: plumberhub-client
Version: 0.3.0
Summary: A Client SDK of PlumberHub impliemented by python
Home-page: https://github.com/lichaozhy/plumberhub-client.git
Author: ChaosLee
Author-email: chaos2lee@qq.com
License: MIT
Platform: UNKNOWN
Classifier: License :: OSI Approved :: MIT License
Classifier: Programming Language :: Python
Classifier: Programming Language :: Python :: 3
Classifier: Programming Language :: Python :: 3.6
Classifier: Programming Language :: Python :: Implementation :: CPython
Classifier: Programming Language :: Python :: Implementation :: PyPy
Requires-Python: >=3.7.0
Requires-Dist: requests
Requires-Dist: websockets
Requires-Dist: protobuf
